MANIFEST.in
README.md
setup.py
pyni/__init__.py
pyni/__main__.py
pyni/benchmarking.py
pyni/config.py
pyni/kernels.py
pyni/simulations.py
pyni.egg-info/PKG-INFO
pyni.egg-info/SOURCES.txt
pyni.egg-info/dependency_links.txt
pyni.egg-info/entry_points.txt
pyni.egg-info/not-zip-safe
pyni.egg-info/requires.txt
pyni.egg-info/top_level.txt
pyni/data/cosmic_20180125.tsv
pyni/data/reactome_FI.txt
pyni/data/reactome_FI_filteredEdges.txt