Metadata-Version: 2.1
Name: pyni
Version: 0.0.8
Summary: Python network inference package
Home-page: https://github.com/dicaso/pyni
Author: Christophe Van Neste
Author-email: christophe.vanneste@ugent.be
License: GNU GENERAL PUBLIC LICENSE
Platform: UNKNOWN
Requires-Python: >3.6
Provides-Extra: development
